drawn/__init__.py
drawn/cli.py
drawn/compiler.py
drawn/config.py
drawn/models.py
drawn/parser.py
drawn/reader.py
drawn/shapes.py
drawn_cli-0.1.1.dist-info/licenses/LICENSE
drawn_cli-0.1.1.dist-info/METADATA
drawn_cli-0.1.1.dist-info/WHEEL
drawn_cli-0.1.1.dist-info/entry_points.txt
drawn_cli-0.1.1.dist-info/top_level.txt
drawn_cli-0.1.1.dist-info/RECORD
