Metadata-Version: 2.4
Name: drawn-cli
Version: 0.1.1
Summary: A minimalistic CLI tool for diagrams-as-code
Author-email: Parthiv R Menon <parthivrmenon@gmail.com>
Maintainer-email: Parthiv R Menon <parthivrmenon@gmail.com>
License: MIT
Project-URL: Homepage, https://github.com/parthivrmenon/drawn
Project-URL: Repository, https://github.com/parthivrmenon/drawn
Project-URL: Issues, https://github.com/parthivrmenon/drawn/issues
Project-URL: Documentation, https://github.com/parthivrmenon/drawn#readme
Project-URL: Changelog, https://github.com/parthivrmenon/drawn/releases
Keywords: diagrams,graphviz,cli,visualization,architecture
Classifier: Development Status :: 3 - Alpha
Classifier: Environment :: Console
Classifier: Intended Audience :: Developers
Classifier: Intended Audience :: System Administrators
Classifier: License :: OSI Approved :: MIT License
Classifier: Operating System :: OS Independent
Classifier: Programming Language :: Python :: 3
Classifier: Programming Language :: Python :: 3.8
Classifier: Programming Language :: Python :: 3.9
Classifier: Programming Language :: Python :: 3.10
Classifier: Programming Language :: Python :: 3.11
Classifier: Programming Language :: Python :: 3.12
Classifier: Topic :: Software Development :: Documentation
Classifier: Topic :: System :: Systems Administration
Classifier: Topic :: Utilities
Requires-Python: >=3.8
License-File: LICENSE
Requires-Dist: graphviz
Provides-Extra: dev
Requires-Dist: pytest; extra == "dev"
Requires-Dist: black; extra == "dev"
Requires-Dist: ruff; extra == "dev"
Provides-Extra: docs
Requires-Dist: mkdocs; extra == "docs"
Requires-Dist: mkdocs-material; extra == "docs"
Dynamic: license-file
